Metadata-Version: 2.1
Name: ezciphers
Version: 0.1
Summary: a set of basic ciphers, e.g. atbash or rot13.
Home-page: 
Author: Tyler Carrothers
Author-email: itxhazrd@gmail.com
License: MIT
Keywords: cipher
Classifier: Development Status :: 3 - Alpha
Classifier: Intended Audience :: Developers
Classifier: Operating System :: OS Independent
Classifier: License :: OSI Approved :: MIT License
Classifier: Programming Language :: Python :: 3
License-File: LICENSE.txt
